PRACTICA 1 DISEÑO DE UNA ALU/fa.v
module fa(output wire c_out, sum, input wire a, b, c_in);
    //Se utiliza la concatenacion como se pedia en el guion
    
    assign {c_out, sum} = a + b + c_in;

endmodule

PRACTICA 1 DISEÑO DE UNA ALU/sum4.v

module sum4(output wire [3:0] S, output wire c_out, input wire[3:0] A, input wire[3:0] B, input wire c_in);

    wire C1, C2, C3;

    fa full_adder0(S[0], C1,A[0], B[0], c_in);
    fa full_adder1(S[1], C2,A[1], B[1], C1);
    fa full_adder2(S[2], C3,A[2], B[2], C2);
    fa full_adder3(S[3], c_out,A[3], B[3], C3);

    

endmodule

mux4_1.v
/*                                               OBJETIVO 1 1.1
        Basándonos en los ejemplos vistos en las sesiones tutorizadas, implementar un multiplexor de 4
                entradas de un bit con el siguiente prototipo:
                          mux4_1(output reg out, input wire a, b, c, d, input wire [1:0] S);*/


module mux4_1(output reg out, input wire a, b, c, d, input wire [1:0] S);
    always @(a,b,c,d,S)
    begin
        case (S)
            2'b00: out = a; 
            2'b01: out = b;
            2'b10: out = c;
            2'b11: out = d;
        endcase
    end


endmodule

cl.v
/*                                           OBJETIVO 2 PARTE 2.1
                          Implementar una “celda lógica” con el prototipo siguiente:
                           cl(output wire out, input wire a, b, input wire [1:0] S);

               Dicha celda lógica calculará sobre los bits a y b las operaciones lógicas and, or, xor e inversión del bit a
                                   cuando el vector de dos bits s vale 00, 01, 10 y 11 respectivamente.*/



module cl(output wire out, input  wire a, b, input wire [1:0] s);

	wire c00, c01, cxor, cnot; // DECLARANDO CABLES DE SALIDA PARA CADA PUERTA RESPECTIVAMENTE
	and	and1(c00, a, b);       //DECLARANDO PUERTA AND
	or	or1(c01, a, b);        //DECLARANDO PUERTA OR
	xor	puertaxor(cxor, a, b); //DECLARANDO PUERTA XOR
	not 	not1(cnot,a);      // DECLARANDO PUERTA NOT
	
	mux4_1 muliplexor1(out, c00, c01, cxor, cnot, s); //MUX 4:1 QUE RECIBE COMO ENTRADA LAS SALIDAS DE LAS PUERTAS LOGICAS REALIZADAS ANTERIORMENTE
	                                                  //  UNA SENAL S Y UNA OUT QUE VIENE DE LA CL

endmodule

ul4.v
/*                                                           OBJETIVO 2 2.2
        Implementar una “unidad lógica de 4 bits” de forma estructural, utilizando las celdas lógicas descritas
                                en el objetivo 2.1. El prototipo sería el siguiente:

                ul4(output wire[3:0] Out, input wire[3:0] A, input wire[3:0] B, input wire [1:0] S);
*/

//NO ENTIENDO MUY BIEN COMO IMPLEMENTAR UNA UNIDAD LOGICA


module ul4(output wire[3:0] Out, input wire[3:0] A, input wire[3:0] B, input wire [1:0] S);
        

        cl and1(Out[0], A[0], B[0], S);
        cl or1(Out[1], A[1], B[1], S);
        cl puertaxor(Out[2], A[2], B[2], S);
        cl not1(Out[3], A[3], B[3], S);
        
        
        

endmodule

compl1.v

//implementar un modulo que nos permita complementar a voluntad en función de una señal de control cpl 
//de forma que podamos dejar pasar un dato sin modificar o hacer su complemento a uno.

module compl1(output wire [3:0] Out, input wire [3:0] Inp, input wire cpl);
  //si cpl = 1, Out = cpl1(Inp) y cuando cpl = 0 la salida Out = Inp
 assign Out = cpl ? (~Inp) : Inp;

endmodule

mux2_4.v
/*                                                     OBJETIVO 1.2. 
            Realiza ahora un multiplexor de 2 entradas a una salida en el que las entradas son de 4 bits. Como ya
        sabes, la línea de selección s determina cuál de las entradas pasa a la salida. El prototipo del módulo es el
                                                        siguiente:
                mux2_4(output wire [3:0] Out, input wire [3:0] A, input wire [3:0] B, input wire s);
*/


module mux2_4(output wire [3:0] Out, input wire [3:0] A, input wire [3:0] B, input wire s);
    assign Out = s ? B : A;
    

endmodule

PRACTICA 1 DISEÑO DE UNA ALU/alu.v
// COMPLETAR LA ALU INTEGRANDO LOS MODULOS ANTERIORMENTE CREADOS






`include "cl.v"
`include "sum4.v"
`include "ul4.v"
`include "compl1.v"
`include "mux4_1.v"
`include "mux2_4.v"
`include "fa.v"




module alu(output wire [3:0] R, output wire zero, carry, sign, input wire [3:0] A, B, input wire [1:0] ALUop, input wire l);

 
    
wire op1_A, op1_B, cpl, cin0;



//CABLEADO DE LOS MULTIPLEXORES

assign op1_A = l | (~ ALUop[1]);
assign op2_B = l | (~ ALUop[1]) | ALUop[0];
assign cpl = (~l) & (~ ALUop[1]) | (~ l) &ALUop[0];
assign cin0 = ALUop[0] | ALUop[1];

assign zero = R == 4'b0000 ? 1'b1 : 1'b0;
assign sign = R[3];

wire [3:0] salidaop1, salida_mux, salidaop2, salidasum4, salidaul4;

//INSTANCIAS DE LOS MULTIPLEXORES Y EL COMPLEMENTADOR


mux2_4 muxA(salidaop1, 4'b0000, A, op1_A);
mux2_4 muxB(salida_mux, A, B, op2_B);
mux2_4 muXC(R,  salidasum4, salidaul4, l);

compl1 complementador(salidaop2, salida_mux, cpl);
ul4 ul10(salidaul4, salidaop1, salidaop2, ALUop);
sum4 sumador(salidaul4, carry, salidaop1, salidaop2,cin0);






endmodule

alu1_tb.v
// Testbench para modulo alu
`timescale 1 ns / 10 ps //Directiva que fija la unidad de tiempo de simulación y la precision de la unidad
module alu_tb;
//declaracion de señales
reg [1:0] t_Op;
reg t_l;
reg [3:0] t_A, t_B;
wire [3:0] t_R;
wire t_z, t_c, t_s;
integer errores;
//instancia del modulo a testear
alu mat(t_R, t_z, t_c, t_s, t_A, t_B, t_Op, t_l);
initial
begin
  $dumpfile("alu.vcd");
  $dumpvars;
  $monitor("tiempo=%0d A=%b B=%b L=%b Op=%b R=%b, Z=%b, C=%b, S=%b", $time, t_A, t_B, t_l, t_Op, t_R, t_z, t_c, t_s);

  errores = 0;
  t_l = 1'b0;
  t_A = 4'b000;
  t_B = 4'b000;
	
	t_Op = 2'b0;
 # 10;
	
  //fin simulacion
  $finish;
end

// Tarea para hacer la comprobación automática de resultados
task check;
reg [4:0] result;
reg flag_zero, flag_carry, flag_sign;
begin
	// Si las operaciones son lógicas
	if (t_l)
	begin
		case (t_Op)
			2'b00: result[3:0] = t_A & t_B;
			2'b01: result[3:0] = t_A | t_B;
			2'b10: result[3:0] = t_A ^ t_B;
			2'b11: result[3:0] = ~t_A;
			default: $display("ERROR. Valor no esperado para t_Op: %b", t_Op);
		endcase
		flag_carry = 1'bx;
		flag_sign = 1'bx;
	end
	else
	begin
		case (t_Op)
			2'b00: result = (t_A ^4'b1111) + 4'b0001;
			2'b01: result = (t_B ^4'b1111) + 4'b0001;
			2'b10: result = t_A + t_B;
			2'b11: result = t_A + ((t_B ^4'b1111) + 1);
			default: $display("ERROR. Valor no esperado para t_Op: %b", t_Op);
		endcase
		flag_carry = result[4];
		flag_sign = result[3];
		if (flag_sign !== t_s || flag_carry !== t_c)
		begin
			errores = errores + 1;
			$display("ERROR con operacion L=%b, OP=%b A=%b B=%b", t_l, t_Op, t_A, t_B);
			if (flag_sign !== t_s)
				$display("ERROR. Flag de signo esperado %b, obtenido %b", flag_sign, t_s);
			if (flag_carry !== t_c)
				$display("\tFlag de acarreo esperado %b, obtenido %b", flag_carry, t_c);
		end
	end

	flag_zero = ~| result[3:0];
	if (result[3:0] !== t_R || flag_zero !== t_z)
	begin
		errores = errores + 1;
		$display("ERROR con operacion L=%b, OP=%b A=%b B=%b", t_l, t_Op, t_A, t_B);
		if (result[3:0] !== t_R)
			$display("\tResultado esperado %b, obtenido %b", result[3:0], t_R);
		if (flag_zero !== t_z)
			$display("\tFlag de cero esperado %b, obtenido %b", flag_zero, t_z);
	end
end
endtask
endmodule

alu.vcd
$date
	Mon Nov  7 18:40:01 2022
$end
$version
	Icarus Verilog
$end
$timescale
	10ps
$end
$scope module alu_tb $end
$var wire 1 ! t_z $end
$var wire 1 " t_s $end
$var wire 1 # t_c $end
$var wire 4 $ t_R [3:0] $end
$var reg 4 % t_A [3:0] $end
$var reg 4 & t_B [3:0] $end
$var reg 2 ' t_Op [1:0] $end
$var reg 1 ( t_l $end
$var integer 32 ) errores [31:0] $end
$scope module mat $end
$var wire 4 * A [3:0] $end
$var wire 2 + ALUop [1:0] $end
$var wire 4 , B [3:0] $end
$var wire 1 - cin0 $end
$var wire 1 . cpl $end
$var wire 1 ( l $end
$var wire 1 / op1_A $end
$var wire 1 0 op2_B $end
$var wire 4 1 salidasum4 [3:0] $end
$var wire 4 2 salidaul4 [3:0] $end
$var wire 1 ! zero $end
$var wire 1 " sign $end
$var wire 4 3 salidaop2 [3:0] $end
$var wire 4 4 salidaop1 [3:0] $end
$var wire 4 5 salida_mux [3:0] $end
$var wire 1 # carry $end
$var wire 4 6 R [3:0] $end
$scope module complementador $end
$var wire 1 . cpl $end
$var wire 4 7 Out [3:0] $end
$var wire 4 8 Inp [3:0] $end
$upscope $end
$scope module muXC $end
$var wire 4 9 A [3:0] $end
$var wire 4 : B [3:0] $end
$var wire 1 ( s $end
$var wire 4 ; Out [3:0] $end
$upscope $end
$scope module muxA $end
$var wire 4 < A [3:0] $end
$var wire 4 = B [3:0] $end
$var wire 1 / s $end
$var wire 4 > Out [3:0] $end
$upscope $end
$scope module muxB $end
$var wire 4 ? A [3:0] $end
$var wire 4 @ B [3:0] $end
$var wire 1 0 s $end
$var wire 4 A Out [3:0] $end
$upscope $end
$scope module sumador $end
$var wire 4 B A [3:0] $end
$var wire 4 C B [3:0] $end
$var wire 4 D S [3:0] $end
$var wire 1 - c_in $end
$var wire 1 # c_out $end
$var wire 1 E C3 $end
$var wire 1 F C2 $end
$var wire 1 G C1 $end
$scope module full_adder0 $end
$var wire 1 H a $end
$var wire 1 I b $end
$var wire 1 - c_in $end
$var wire 1 G sum $end
$var wire 1 J c_out $end
$upscope $end
$scope module full_adder1 $end
$var wire 1 K a $end
$var wire 1 L b $end
$var wire 1 G c_in $end
$var wire 1 F sum $end
$var wire 1 M c_out $end
$upscope $end
$scope module full_adder2 $end
$var wire 1 N a $end
$var wire 1 O b $end
$var wire 1 F c_in $end
$var wire 1 E sum $end
$var wire 1 P c_out $end
$upscope $end
$scope module full_adder3 $end
$var wire 1 Q a $end
$var wire 1 R b $end
$var wire 1 E c_in $end
$var wire 1 # sum $end
$var wire 1 S c_out $end
$upscope $end
$upscope $end
$scope module ul10 $end
$var wire 4 T A [3:0] $end
$var wire 4 U B [3:0] $end
$var wire 4 V Out [3:0] $end
$var wire 2 W S [1:0] $end
$scope module and1 $end
$var wire 1 X a $end
$var wire 1 Y b $end
$var wire 1 Z c00 $end
$var wire 1 [ c01 $end
$var wire 1 \ cnot $end
$var wire 1 ] cxor $end
$var wire 2 ^ s [1:0] $end
$var wire 1 _ out $end
$scope module muliplexor1 $end
$var wire 2 ` S [1:0] $end
$var wire 1 Z a $end
$var wire 1 [ b $end
$var wire 1 ] c $end
$var wire 1 \ d $end
$var reg 1 _ out $end
$upscope $end
$upscope $end
$scope module not1 $end
$var wire 1 a a $end
$var wire 1 b b $end
$var wire 1 c c00 $end
$var wire 1 d c01 $end
$var wire 1 e cnot $end
$var wire 1 f cxor $end
$var wire 2 g s [1:0] $end
$var wire 1 h out $end
$scope module muliplexor1 $end
$var wire 2 i S [1:0] $end
$var wire 1 c a $end
$var wire 1 d b $end
$var wire 1 f c $end
$var wire 1 e d $end
$var reg 1 h out $end
$upscope $end
$upscope $end
$scope module or1 $end
$var wire 1 j a $end
$var wire 1 k b $end
$var wire 1 l c00 $end
$var wire 1 m c01 $end
$var wire 1 n cnot $end
$var wire 1 o cxor $end
$var wire 2 p s [1:0] $end
$var wire 1 q out $end
$scope module muliplexor1 $end
$var wire 2 r S [1:0] $end
$var wire 1 l a $end
$var wire 1 m b $end
$var wire 1 o c $end
$var wire 1 n d $end
$var reg 1 q out $end
$upscope $end
$upscope $end
$scope module puertaxor $end
$var wire 1 s a $end
$var wire 1 t b $end
$var wire 1 u c00 $end
$var wire 1 v c01 $end
$var wire 1 w cnot $end
$var wire 1 x cxor $end
$var wire 2 y s [1:0] $end
$var wire 1 z out $end
$scope module muliplexor1 $end
$var wire 2 { S [1:0] $end
$var wire 1 u a $end
$var wire 1 v b $end
$var wire 1 x c $end
$var wire 1 w d $end
$var reg 1 z out $end
$upscope $end
$upscope $end
$upscope $end
$upscope $end
$scope task check $end
$var reg 1 | flag_carry $end
$var reg 1 } flag_sign $end
$var reg 1 ~ flag_zero $end
$var reg 5 !" result [4:0] $end
$upscope $end
$upscope $end
$enddefinitions $end
#0
$dumpvars
bx !"
x~
x}
x|
b0 {
0z
b0 y
1x
1w
1v
0u
1t
0s
b0 r
0q
b0 p
1o
1n
1m
0l
1k
0j
b0 i
0h
b0 g
1f
1e
1d
0c
1b
0a
b0 `
0_
b0 ^
1]
1\
1[
0Z
1Y
0X
b0 W
bx0x0 V
b1111 U
b0 T
1S
1R
0Q
0P
1O
0N
1M
1L
0K
0J
1I
0H
1G
0F
1E
bx0x0 D
b1111 C
b0 B
b0 A
b0 @
b0 ?
b0 >
b0 =
b0 <
bz ;
bx0x0 :
bz 9
b0 8
b1111 7
bz 6
b0 5
b0 4
b1111 3
bx0x0 2
bz 1
10
1/
1.
0-
b0 ,
b0 +
b0 *
b0 )
0(
b0 '
b0 &
b0 %
bz $
0#
z"
x!
$end
#200
1#
0S
0E
1P
1F
b0x00 2
b0x00 :
b0x00 D
b0x00 V
0M
0G
0[
0]
0I
0Y
b1110 3
b1110 7
b1110 C
b1110 U
b1 5
b1 8
b1 A
b1 &
b1 ,
b1 @
1~
b10 )
0}
1|
b10000 !"
#400
1#
0S
0E
b0x00 2
b0x00 :
b0x00 D
b0x00 V
1P
1G
1F
1[
1]
0m
0o
1I
0L
1Y
0k
b1101 3
b1101 7
b1101 C
b1101 U
b10 5
b10 8
b10 A
b10 &
b10 ,
b10 @
b100 )
#600
0#
1S
1E
bx000 2
bx000 :
bx000 D
bx000 V
0P
0F
0G
0[
0]
0I
0Y
b1100 3
b1100 7
b1100 C
b1100 U
b11 5
b11 8
b11 A
b11 &
b11 ,
b11 @
b110 )
#800
1M
1#
b0x0 2
b0x0 :
b0x0 D
b0x0 V
0S
1G
0F
0E
1[
1]
1m
1o
0v
0x
1I
1L
0O
1Y
1k
0t
b1011 3
b1011 7
b1011 C
b1011 U
b100 5
b100 8
b100 A
b100 &
b100 ,
b100 @
b1000 )
#1000
0#
1S
1E
1F
bx000 2
bx000 :
bx000 D
bx000 V
0M
0G
0[
0]
0I
0Y
b1010 3
b1010 7
b1010 C
b1010 U
b101 5
b101 8
b101 A
b101 &
b101 ,
b101 @
b1010 )
#1200
0#
bx000 2
bx000 :
bx000 D
bx000 V
1S
1E
1G
1F
1[
1]
0m
0o
1I
0L
1Y
0k
b1001 3
b1001 7
b1001 C
b1001 U
b110 5
b110 8
b110 A
b110 &
b110 ,
b110 @
b1100 )
#1400
1#
b0 2
b0 :
b0 D
b0 V
0S
0E
0F
0G
0[
0]
0I
0Y
b1000 3
b1000 7
b1000 C
b1000 U
b111 5
b111 8
b111 A
b111 &
b111 ,
b111 @
b1110 )
#1600
1M
b0x0 2
b0x0 :
b0x0 D
b0x0 V
0P
1G
0F
1E
1#
1[
1]
1m
1o
1v
1x
0d
0f
1I
1L
1O
0R
1Y
1k
1t
0b
b111 3
b111 7
b111 C
b111 U
b1000 5
b1000 8
b1000 A
b1000 &
b1000 ,
b1000 @
b10000 )
#1800
0#
0E
1P
1F
b0x00 2
b0x00 :
b0x00 D
b0x00 V
0M
0G
0[
0]
0I
0Y
b110 3
b110 7
b110 C
b110 U
b1001 5
b1001 8
b1001 A
b1001 &
b1001 ,
b1001 @
b10010 )
#2000
0#
0E
b0x00 2
b0x00 :
b0x00 D
b0x00 V
1P
1G
1F
1[
1]
0m
0o
1I
0L
1Y
0k
b101 3
b101 7
b101 C
b101 U
b1010 5
b1010 8
b1010 A
b1010 &
b1010 ,
b1010 @
b10100 )
#2200
1#
1E
b0 2
b0 :
b0 D
b0 V
0P
0F
0G
0[
0]
0I
0Y
b100 3
b100 7
b100 C
b100 U
b1011 5
b1011 8
b1011 A
b1011 &
b1011 ,
b1011 @
b10110 )
#2400
b0x0 2
b0x0 :
b0x0 D
b0x0 V
1M
0#
1G
0F
0E
1[
1]
1m
1o
0v
0x
1I
1L
0O
1Y
1k
0t
b11 3
b11 7
b11 C
b11 U
b1100 5
b1100 8
b1100 A
b1100 &
b1100 ,
b1100 @
b11000 )
#2600
1#
1E
1F
b0 2
b0 :
b0 D
b0 V
0M
0G
0[
0]
0I
0Y
b10 3
b10 7
b10 C
b10 U
b1101 5
b1101 8
b1101 A
b1101 &
b1101 ,
b1101 @
b11010 )
#2800
1#
1E
1G
1F
1[
1]
0m
0o
1I
0L
1Y
0k
b1 3
b1 7
b1 C
b1 U
b1110 5
b1110 8
b1110 A
b1110 &
b1110 ,
b1110 @
b11100 )
#3000
0#
0E
0F
0G
0[
0]
0I
0Y
b0 3
b0 7
b0 C
b0 U
b1111 5
b1111 8
b1111 A
b1111 &
b1111 ,
b1111 @
b11110 )
#3200
1P
1F
0S
1_
1J
b0x01 2
b0x01 :
b0x01 D
b0x01 V
0M
0E
1#
1Z
1m
1o
1v
1x
1d
1f
1I
1L
1O
1R
1Y
1k
1t
1b
0G
1[
0]
0\
b1111 3
b1111 7
b1111 C
b1111 U
1H
1X
b1 4
b1 >
b1 B
b1 T
b0 5
b0 8
b0 A
b1 %
b1 *
b1 =
b1 ?
b0 &
b0 ,
b0 @
b100000 )
#3400
0#
1S
1E
0P
0F
1M
0_
1G
bx0x0 2
bx0x0 :
bx0x0 D
bx0x0 V
0J
0Z
1]
0I
0Y
b1110 3
b1110 7
b1110 C
b1110 U
b1 5
b1 8
b1 A
b1 &
b1 ,
b1 @
0~
b100010 )
1}
0|
b1111 !"
#3600
0#
1S
1E
0P
1_
0G
1J
0F
bx001 2
bx001 :
bx001 D
bx001 V
0M
1Z
0]
0m
0o
1I
0L
1Y
0k
b1101 3
b1101 7
b1101 C
b1101 U
b10 5
b10 8
b10 A
b10 &
b10 ,
b10 @
b100100 )
#3800
1#
0S
0E
1P
1F
0_
1G
b0x00 2
b0x00 :
b0x00 D
b0x00 V
0J
0Z
1]
0I
0Y
b1100 3
b1100 7
b1100 C
b1100 U
b11 5
b11 8
b11 A
b11 &
b11 ,
b11 @
b100110 )
#4000
0#
1S
1_
0G
1J
1F
0M
1E
bx001 2
bx001 :
bx001 D
bx001 V
0P
1Z
0]
1m
1o
0v
0x
1I
1L
0O
1Y
1k
0t
b1011 3
b1011 7
b1011 C
b1011 U
b100 5
b100 8
b100 A
b100 &
b100 ,
b100 @
b101000 )
#4200
1#
0S
0E
0F
1M
0_
1G
b0x0 2
b0x0 :
b0x0 D
b0x0 V
0J
0Z
1]
0I
0Y
b1010 3
b1010 7
b1010 C
b1010 U
b101 5
b101 8
b101 A
b101 &
b101 ,
b101 @
b101010 )
#4400
1#
0S
0E
1_
0G
1J
0F
b1 2
b1 :
b1 D
b1 V
0M
1Z
0]
0m
0o
1I
0L
1Y
0k
b1001 3
b1001 7
b1001 C
b1001 U
b110 5
b110 8
b110 A
b110 &
b110 ,
b110 @
b101100 )
#4600
0#
1S
1E
1F
0_
1G
bx000 2
bx000 :
bx000 D
bx000 V
0J
0Z
1]
0I
0Y
b1000 3
b1000 7
b1000 C
b1000 U
b111 5
b111 8
b111 A
b111 &
b111 ,
b111 @
b101110 )
#4800
1_
0G
1J
1F
0M
0E
1P
0#
b0x01 2
b0x01 :
b0x01 D
b0x01 V
0S
1Z
0]
1m
1o
1v
1x
0d
0f
1I
1L
1O
0R
1Y
1k
1t
0b
b111 3
b111 7
b111 C
b111 U
b1000 5
b1000 8
b1000 A
b1000 &
b1000 ,
b1000 @
b110000 )
#5000
1#
1E
0P
0F
1M
0_
1G
b0x0 2
b0x0 :
b0x0 D
b0x0 V
0J
0Z
1]
0I
0Y
b110 3
b110 7
b110 C
b110 U
b1001 5
b1001 8
b1001 A
b1001 &
b1001 ,
b1001 @
b110010 )
#5200
1#
1E
0P
1_
0G
1J
0F
b1 2
b1 :
b1 D
b1 V
0M
1Z
0]
0m
0o
1I
0L
1Y
0k
b101 3
b101 7
b101 C
b101 U
b1010 5
b1010 8
b1010 A
b1010 &
b1010 ,
b1010 @
b110100 )
#5400
0#
0E
1P
1F
0_
1G
b0x00 2
b0x00 :
b0x00 D
b0x00 V
0J
0Z
1]
0I
0Y
b100 3
b100 7
b100 C
b100 U
b1011 5
b1011 8
b1011 A
b1011 &
b1011 ,
b1011 @
b110110 )
#5600
1#
1_
0G
1J
1F
0M
1E
b1 2
b1 :
b1 D
b1 V
0P
1Z
0]
1m
1o
0v
0x
1I
1L
0O
1Y
1k
0t
b11 3
b11 7
b11 C
b11 U
b1100 5
b1100 8
b1100 A
b1100 &
b1100 ,
b1100 @
b111000 )
#5800
0#
0E
0F
1M
0_
1G
b0x0 2
b0x0 :
b0x0 D
b0x0 V
0J
0Z
1]
0I
0Y
b10 3
b10 7
b10 C
b10 U
b1101 5
b1101 8
b1101 A
b1101 &
b1101 ,
b1101 @
b111010 )
#6000
0#
0E
1_
0G
1J
0F
b1 2
b1 :
b1 D
b1 V
0M
1Z
0]
0m
0o
1I
0L
1Y
0k
b1 3
b1 7
b1 C
b1 U
b1110 5
b1110 8
b1110 A
b1110 &
b1110 ,
b1110 @
b111100 )
#6200
1#
1E
1F
0_
1G
b0 2
b0 :
b0 D
b0 V
0J
0Z
1]
0I
0Y
b0 3
b0 7
b0 C
b0 U
b1111 5
b1111 8
b1111 A
b1111 &
b1111 ,
b1111 @
b111110 )
#6400
0E
1P
1q
1#
0S
1l
1v
1x
1d
1f
1I
1L
1O
1R
1Y
1k
1t
1b
1G
1F
b0x10 2
b0x10 :
b0x10 D
b0x10 V
1M
1[
1]
1\
1m
0o
0n
b1111 3
b1111 7
b1111 C
b1111 U
0H
1K
0X
1j
b10 4
b10 >
b10 B
b10 T
b0 5
b0 8
b0 A
b10 %
b10 *
b10 =
b10 ?
b0 &
b0 ,
b0 @
b1000000 )
#6600
0#
1S
1E
bx010 2
bx010 :
bx010 D
bx010 V
0P
0F
0G
0[
0]
0I
0Y
b1110 3
b1110 7
b1110 C
b1110 U
b1 5
b1 8
b1 A
b1 &
b1 ,
b1 @
b1000010 )
b1110 !"
#6800
0#
1S
1E
0P
0q
1G
0F
bx0x0 2
bx0x0 :
bx0x0 D
bx0x0 V
1M
1[
1]
0l
1o
1I
0L
1Y
0k
b1101 3
b1101 7
b1101 C
b1101 U
b10 5
b10 8
b10 A
b10 &
b10 ,
b10 @
b1000100 )
#7000
1#
0S
0E
1P
1F
b0x00 2
b0x00 :
b0x00 D
b0x00 V
0M
0G
0[
0]
0I
0Y
b1100 3
b1100 7
b1100 C
b1100 U
b11 5
b11 8
b11 A
b11 &
b11 ,
b11 @
b1000110 )
#7200
0#
1S
1q
1G
1F
1M
1E
bx010 2
bx010 :
bx010 D
bx010 V
0P
1[
1]
1l
0o
0v
0x
1I
1L
0O
1Y
1k
0t
b1011 3
b1011 7
b1011 C
b1011 U
b100 5
b100 8
b100 A
b100 &
b100 ,
b100 @
b1001000 )
#7400
1#
b10 2
b10 :
b10 D
b10 V
0S
0E
0F
0G
0[
0]
0I
0Y
b1010 3
b1010 7
b1010 C
b1010 U
b101 5
b101 8
b101 A
b101 &
b101 ,
b101 @
b1001010 )
#7600
1#
0S
0E
0q
1G
0F
b0x0 2
b0x0 :
b0x0 D
b0x0 V
1M
1[
1]
0l
1o
1I
0L
1Y
0k
b1001 3
b1001 7
b1001 C
b1001 U
b110 5
b110 8
b110 A
b110 &
b110 ,
b110 @
b1001100 )
#7800
0#
1S
1E
1F
bx000 2
bx000 :
bx000 D
bx000 V
0M
0G
0[
0]
0I
0Y
b1000 3
b1000 7
b1000 C
b1000 U
b111 5
b111 8
b111 A
b111 &
b111 ,
b111 @
b1001110 )
#8000
1q
1G
1F
1M
0E
1P
0#
b0x10 2
b0x10 :
b0x10 D
b0x10 V
0S
1[
1]
1l
0o
1v
1x
0d
0f
1I
1L
1O
0R
1Y
1k
1t
0b
b111 3
b111 7
b111 C
b111 U
b1000 5
b1000 8
b1000 A
b1000 &
b1000 ,
b1000 @
b1010000 )
#8200
1#
1E
b10 2
b10 :
b10 D
b10 V
0P
0F
0G
0[
0]
0I
0Y
b110 3
b110 7
b110 C
b110 U
b1001 5
b1001 8
b1001 A
b1001 &
b1001 ,
b1001 @
b1010010 )
#8400
1#
1E
0P
0q
1G
0F
b0x0 2
b0x0 :
b0x0 D
b0x0 V
1M
1[
1]
0l
1o
1I
0L
1Y
0k
b101 3
b101 7
b101 C
b101 U
b1010 5
b1010 8
b1010 A
b1010 &
b1010 ,
b1010 @
b1010100 )
#8600
0#
0E
1P
1F
b0x00 2
b0x00 :
b0x00 D
b0x00 V
0M
0G
0[
0]
0I
0Y
b100 3
b100 7
b100 C
b100 U
b1011 5
b1011 8
b1011 A
b1011 &
b1011 ,
b1011 @
b1010110 )
#8800
1#
1q
1G
1F
1M
1E
b10 2
b10 :
b10 D
b10 V
0P
1[
1]
1l
0o
0v
0x
1I
1L
0O
1Y
1k
0t
b11 3
b11 7
b11 C
b11 U
b1100 5
b1100 8
b1100 A
b1100 &
b1100 ,
b1100 @
b1011000 )
#9000
0#
0E
0F
0G
0[
0]
0I
0Y
b10 3
b10 7
b10 C
b10 U
b1101 5
b1101 8
b1101 A
b1101 &
b1101 ,
b1101 @
b1011010 )
#9200
0#
0E
0q
1G
0F
b0x0 2
b0x0 :
b0x0 D
b0x0 V
1M
1[
1]
0l
1o
1I
0L
1Y
0k
b1 3
b1 7
b1 C
b1 U
b1110 5
b1110 8
b1110 A
b1110 &
b1110 ,
b1110 @
b1011100 )
#9400
1#
1E
1F
b0 2
b0 :
b0 D
b0 V
0M
0G
0[
0]
0I
0Y
b0 3
b0 7
b0 C
b0 U
b1111 5
b1111 8
b1111 A
b1111 &
b1111 ,
b1111 @
b1011110 )
#9600
0F
1_
1q
1J
1E
0P
0#
1S
1Z
1l
0o
1v
1x
1d
1f
bx011 2
bx011 :
bx011 D
bx011 V
1M
1I
1L
1O
1R
1Y
1k
1t
1b
0G
1[
0]
0\
b1111 3
b1111 7
b1111 C
b1111 U
1H
1X
b11 4
b11 >
b11 B
b11 T
b0 5
b0 8
b0 A
b11 %
b11 *
b11 =
b11 ?
b0 &
b0 ,
b0 @
b1100000 )
#9800
1#
0S
0E
1P
1F
0_
1G
b0x10 2
b0x10 :
b0x10 D
b0x10 V
0J
0Z
1]
0I
0Y
b1110 3
b1110 7
b1110 C
b1110 U
b1 5
b1 8
b1 A
b1 &
b1 ,
b1 @
b1100010 )
b1101 !"
#10000
1#
0S
0M
0E
1P
1_
0q
0G
b0x01 2
b0x01 :
b0x01 D
b0x01 V
1J
1F
1Z
0]
0l
1o
1I
0L
1Y
0k
b1101 3
b1101 7
b1101 C
b1101 U
b10 5
b10 8
b10 A
b10 &
b10 ,
b10 @
b1100100 )
#10200
0#
1S
1E
0P
0F
1M
0_
1G
bx0x0 2
bx0x0 :
bx0x0 D
bx0x0 V
0J
0Z
1]
0I
0Y
b1100 3
b1100 7
b1100 C
b1100 U
b11 5
b11 8
b11 A
b11 &
b11 ,
b11 @
b1100110 )
#10400
1#
0S
1_
1q
0G
b11 2
b11 :
b11 D
b11 V
1J
0F
0E
1Z
0]
1l
0o
0v
0x
1I
1L
0O
1Y
1k
0t
b1011 3
b1011 7
b1011 C
b1011 U
b100 5
b100 8
b100 A
b100 &
b100 ,
b100 @
b1101000 )
#10600
0#
1S
1E
1F
0_
1G
bx010 2
bx010 :
bx010 D
bx010 V
0J
0Z
1]
0I
0Y
b1010 3
b1010 7
b1010 C
b1010 U
b101 5
b101 8
b101 A
b101 &
b101 ,
b101 @
b1101010 )
#10800
0#
1S
0M
1E
1_
0q
0G
bx001 2
bx001 :
bx001 D
bx001 V
1J
1F
1Z
0]
0l
1o
1I
0L
1Y
0k
b1001 3
b1001 7
b1001 C
b1001 U
b110 5
b110 8
b110 A
b110 &
b110 ,
b110 @
b1101100 )
#11000
1#
0S
0E
0F
1M
0_
1G
b0x0 2
b0x0 :
b0x0 D
b0x0 V
0J
0Z
1]
0I
0Y
b1000 3
b1000 7
b1000 C
b1000 U
b111 5
b111 8
b111 A
b111 &
b111 ,
b111 @
b1101110 )
#11200
0P
1_
1q
0G
b11 2
b11 :
b11 D
b11 V
1J
0F
1E
1#
1Z
0]
1l
0o
1v
1x
0d
0f
1I
1L
1O
0R
1Y
1k
1t
0b
b111 3
b111 7
b111 C
b111 U
b1000 5
b1000 8
b1000 A
b1000 &
b1000 ,
b1000 @
b1110000 )
#11400
0#
0E
1P
1F
0_
1G
b0x10 2
b0x10 :
b0x10 D
b0x10 V
0J
0Z
1]
0I
0Y
b110 3
b110 7
b110 C
b110 U
b1001 5
b1001 8
b1001 A
b1001 &
b1001 ,
b1001 @
b1110010 )
#11600
0#
0M
0E
1P
1_
0q
0G
b0x01 2
b0x01 :
b0x01 D
b0x01 V
1J
1F
1Z
0]
0l
1o
1I
0L
1Y
0k
b101 3
b101 7
b101 C
b101 U
b1010 5
b1010 8
b1010 A
b1010 &
b1010 ,
b1010 @
b1110100 )
#11800
1#
1E
0P
0F
1M
0_
1G
b0x0 2
b0x0 :
b0x0 D
b0x0 V
0J
0Z
1]
0I
0Y
b100 3
b100 7
b100 C
b100 U
b1011 5
b1011 8
b1011 A
b1011 &
b1011 ,
b1011 @
b1110110 )
#12000
0#
1_
1q
0G
b11 2
b11 :
b11 D
b11 V
1J
0F
0E
1Z
0]
1l
0o
0v
0x
1I
1L
0O
1Y
1k
0t
b11 3
b11 7
b11 C
b11 U
b1100 5
b1100 8
b1100 A
b1100 &
b1100 ,
b1100 @
b1111000 )
